nitro_validator/__init__.py
nitro_validator/py.typed
nitro_validator/core/__init__.py
nitro_validator/core/exceptions.py
nitro_validator/core/rule.py
nitro_validator/core/rule_registry.py
nitro_validator/core/validator.py
nitro_validator/utils/__init__.py
nitro_validator/utils/rules.py
nitro_validator-1.0.1.dist-info/licenses/LICENSE
nitro_validator-1.0.1.dist-info/METADATA
nitro_validator-1.0.1.dist-info/WHEEL
nitro_validator-1.0.1.dist-info/top_level.txt
nitro_validator-1.0.1.dist-info/RECORD
