Metadata-Version: 2.4
Name: nitro-validator
Version: 1.0.1
Summary: A powerful, standalone, dependency-free data validation library for Python with extensible rules and a clean, intuitive API.
Author-email: Sean Nieuwoudt <sean@nitro.sh>
License: BSD-3-Clause
Project-URL: Homepage, https://github.com/nitro/nitro-validator
Project-URL: Documentation, https://github.com/nitro/nitro-validator/blob/main/README.md
Project-URL: Repository, https://github.com/nitro/nitro-validator
Project-URL: Issues, https://github.com/nitro/nitro-validator/issues
Keywords: validation,validator,data-validation,form-validation,input-validation
Classifier: Operating System :: OS Independent
Classifier: Development Status :: 5 - Production/Stable
Classifier: Intended Audience :: Developers
Classifier: Programming Language :: Python :: 3
Classifier: Programming Language :: Python :: 3.7
Classifier: Programming Language :: Python :: 3.8
Classifier: Programming Language :: Python :: 3.9
Classifier: Programming Language :: Python :: 3.10
Classifier: Programming Language :: Python :: 3.11
Classifier: Programming Language :: Python :: 3.12
Classifier: Programming Language :: Python :: 3.13
Classifier: Programming Language :: Python :: 3.14
Classifier: Topic :: Software Development :: Libraries :: Python Modules
Classifier: Topic :: Software Development :: Libraries
Requires-Python: >=3.7
License-File: LICENSE
Provides-Extra: dev
Requires-Dist: pytest>=7.0; extra == "dev"
Requires-Dist: pytest-cov>=4.0; extra == "dev"
Requires-Dist: black>=22.0; extra == "dev"
Requires-Dist: flake8>=5.0; extra == "dev"
Requires-Dist: mypy>=0.990; extra == "dev"
Dynamic: license-file
